projetos-digitais/trabalho/mico.vhd
-- ++++++++++++++++++++++++++++++++++++++++++++++++++++++++++++++++++++++++
-- UFPR, BCC, ci210 2017-2 trabalho semestral, autor: Roberto Hexsel, 21out
-- ++++++++++++++++++++++++++++++++++++++++++++++++++++++++++++++++++++++++


-- +++++++++++++++++++++++++++++++++++++++++++++++++++++++++++++++++++
-- processador MICO XI
-- +++++++++++++++++++++++++++++++++++++++++++++++++++++++++++++++++++
library ieee; use ieee.std_logic_1164.all;
use IEEE.numeric_std.all;
use work.p_wires.all;


entity mico is
  port (rst,clk : in bit);
end mico;

architecture functional of mico is

  component mem_prog is                 -- no arquivo mem.vhd
    port (ender : in  reg7;
          instr : out reg32);
  end component mem_prog;

  component display is                  -- neste arquivo
    port (rst,clk : in bit;
          enable  : in bit;
          data    : in reg32);
  end component display;

  component ULA is                      -- neste arquivo
    port (fun : in reg4;
          alfa,beta : in  reg32;
          gama      : out reg32);
  end component ULA;
 
  component R is                        -- neste arquivo
    port (clk         : in  bit;
          wr_en       : in  bit;
          r_a,r_b,r_c : in  reg4;
          A,B         : out reg32;
          C           : in  reg32);
  end component R;

  component RAM is                      -- neste arquivo
    port (rst, clk : in  bit;
          sel      : in  bit;           -- ativo em 1
          wr       : in  bit;           -- ativo em 1
          ender    : in  reg16;
          data_inp : in  reg32;
          data_out : out reg32);
  end component RAM;


  type t_control_type is record
    selC       : reg2;     -- seleciona fonte da escrita no reg destino
    wr_reg     : bit;      -- atualiza banco de registradores
    selBeta    : bit;      -- seleciona fonte para entrada B da ULA
    mem_sel    : bit;      -- habilita acesso a RAM
    mem_wr     : bit;      -- habilita escrita na RAM
  end record;

  type t_control_mem is array (0 to 15) of t_control_type;
  
  constant ctrl_table : t_control_mem := (
  -- selC  WrR  selB MSel MWr
    ("11", '0', '0', '0', '0'),            -- NOP
    ("00", '1', '0', '0', '0'),            -- ADD
    ("00", '1', '0', '0', '0'),            -- SUB
    ("00", '1', '0', '0', '0'),            -- MUL
    ("00", '1', '0', '0', '0'),            -- AND
    ("00", '1', '0', '0', '0'),            -- OR
    ("00", '1', '0', '0', '0'),            -- XOR
    ("00", '1', '0', '0', '0'),            -- NOT
    ("00", '1', '1', '0', '0'),            -- ADDI
    ("00", '1', '0', '0', '0'),            -- SRA
    ("01", '1', '1', '1', '0'),            -- LD
    ("11", '0', '1', '1', '1'),            -- ST
    ("11", '0', '1', '0', '0'),            -- BRANCH
    ("10", '1', '1', '0', '0'),            -- JAL
    ("11", '0', '0', '0', '0'),            -- JR
    ("11", '0', '0', '0', '0'));           -- HALT

  constant op_BRA  : bit_vector := x"c";
  constant op_JAL  : bit_vector := x"d";
  constant op_JR   : bit_vector := x"e";
  constant op_HALT : bit_vector := x"f";

  subtype sml_int is integer range 0 to 65535;
  
  signal selC : reg2;
  signal selBeta, wr_display, wr_reg : bit;
  signal is_mem, mem_sel, mem_wr : bit;

  signal instr, A, B, C, beta, extended, ula_D, mem_D : reg32;
  signal this  : t_control_type;
  signal const, ip, ip_mais1, ext_zeros, ext_sinal : reg16;
  signal opcode : reg4;
  signal i_opcode : natural range 0 to 15;
  signal reg_a, reg_b, reg_c : reg4;
  
begin  -- functional

  -- controla IP
  U_ip: process (clk, rst, opcode, const, A, B)
    variable i_ip    : sml_int := 0;
    variable i_ip_m1 : sml_int := 0;
  begin
    if rst = '1' then
      i_ip := 0;
    else
      if rising_edge(clk) then
        if (opcode = op_JAL) then -- jal
          i_ip    := BV2INT16(const);
        elsif (opcode = op_JR) then -- jr
          i_ip := BV2INT16(A(15 downto 0));
        elsif (opcode = op_BRA) then 
          if (A = B) then                -- branch taken
            i_ip := BV2INT16(const);
          else                           -- branch not-taken
            i_ip := i_ip + 1;
          end if;
        elsif opcode = op_HALT then         -- halt
          i_ip := i_ip + 0;

          assert opcode /= op_HALT
            report LF & LF & "simulation halted: " & 
            "ender = "&integer'image(BV2INT16(ip))&" = "&BV16HEX(ip)&LF
            severity failure;

        else
          i_ip    := i_ip + 1;
          i_ip_m1 := i_ip + 1;
        end if;
      end if;
    end if;
    ip       <= INT2BV16(i_ip);
    ip_mais1 <= INT2BV16(i_ip_m1);
  end process U_ip; 
  

  -- memoria de programa contem somente 128 palavras
  U_mem_prog: mem_prog port map(ip(6 downto 0), instr);

  
  opcode   <= instr(31 downto 28);
  i_opcode <= BV2INT4(opcode);          -- indice do vetor DEVE ser inteiro
  const    <= instr(15 downto 0);
  
  this     <= ctrl_table(i_opcode);         -- sinais de controle

  selBeta  <= this.selBeta;
  wr_reg   <= this.wr_reg;
  selC     <= this.selC;
  is_mem   <= this.mem_sel;
  mem_wr   <= this.mem_wr;

  reg_a    <= instr(27 downto 24);
  reg_b    <= instr(23 downto 20);
  reg_c    <= instr(19 downto 16);
  
  ext_sinal <= x"0000" when instr(15) = '0' else
               x"ffff";
  
  extended <= ext_sinal & instr(15 downto 0);
  
  beta <= B when selBeta = '0' else extended;

  with selC select
    C <= ula_D              when "00",   -- ULA
         mem_D              when "01",   -- LD 
         x"0000" & ip_mais1 when "10",   -- JAL
         x"00000000"        when others; -- nil
  
  U_regs: R port map (clk, wr_reg, reg_a, reg_b, reg_c,
                      A,B,C);

  U_ULA: ULA port map (opcode, A, beta, ula_D);

  U_mem: RAM port map (rst, clk, mem_sel, mem_wr,
                       ula_D(15 downto 0), B, mem_D);
  
  mem_sel <= '1' when ( (ula_D(15 downto 0) /= x"ffff")
                        and (is_mem = '1')              ) else
             '0';

  wr_display <= '1' when ( (ula_D(15 downto 0) = x"ffff") and
                           (is_mem  = '1')                and
                           (mem_wr  = '1')                    ) else
                '0';
    
  U_display: display port map (rst, clk, wr_display, B);

  
end functional;
-- +++++++++++++++++++++++++++++++++++++++++++++++++++++++++++++++++++




-- +++++++++++++++++++++++++++++++++++++++++++++++++++++++++++++++++++
library IEEE; use ieee.std_logic_1164.all;
use work.p_wires.all;

entity ULA is
  port (fun : in reg4;
        alfa,beta : in  reg32;
        gama      : out reg32);
end ULA;

architecture behaviour of ULA is
  signal a,b,c, sh_pos : integer;
begin  -- behaviour

  a <= BV2INT(alfa);
  b <= BV2INT(beta);

  sh_pos <= BV2INT5(beta(4 downto 0));
  
  with fun select
    gama <= (others => '0')   when "0000",
            INT2BV32( a + b ) when "0001",
            INT2BV32( a - b ) when "0010",
            INT2BV32( a * b ) when "0011",
            alfa and beta     when "0100",
            alfa or  beta     when "0101",
            alfa xor beta     when "0110",
            not(alfa)         when "0111",
            INT2BV32( a + b ) when "1000",
            alfa sra sh_pos   when "1001",
            INT2BV32( a + b ) when "1010",
            INT2BV32( a + b ) when "1011",
            (others => '0')   when others;

end behaviour;
-- -----------------------------------------------------------------------



-- +++++++++++++++++++++++++++++++++++++++++++++++++++++++++++++++++++
-- display: exibe inteiro na saida padrao do simulador
--          NAO ALTERE ESTE MODELO
-- +++++++++++++++++++++++++++++++++++++++++++++++++++++++++++++++++++
library IEEE; use std.textio.all;
use work.p_wires.all;

entity display is
  port (rst,clk : in bit;
        enable  : in bit;
        data    : in reg32);
end display;

architecture functional of display is
  file output : text open write_mode is "STD_OUTPUT";
begin  -- functional

  U_WRITE_OUT: process(clk)
    variable msg : line;
  begin
    if falling_edge(clk) and enable = '1' then
      write ( msg, string'(BV32HEX(data)) );
      writeline( output, msg );
    end if;
  end process U_WRITE_OUT;

end functional;
-- ++ display ++++++++++++++++++++++++++++++++++++++++++++++++++++++++



-- +++++++++++++++++++++++++++++++++++++++++++++++++++++++++++++++++++
-- memoria RAM, com capacidade de 64K palavras de 32 bits
--          NAO ALTERE ESTE MODELO
-- +++++++++++++++++++++++++++++++++++++++++++++++++++++++++++++++++++
library ieee; use ieee.std_logic_1164.all;
use IEEE.numeric_std.all;
use work.p_wires.all;

entity RAM is
  port (rst, clk : in  bit;
        sel      : in  bit;          -- ativo em 1
        wr       : in  bit;          -- ativo em 1
        ender    : in  reg16;
        data_inp : in  reg32;
        data_out : out reg32);

  constant DATA_MEM_SZ : natural := 2**16;
  constant DATA_ADDRS_BITS : natural := log2_ceil(DATA_MEM_SZ);

end RAM;

architecture rtl of RAM is
  
  subtype t_address is unsigned((DATA_ADDRS_BITS - 1) downto 0);
  
  subtype word is bit_vector(31 downto 0);
  type storage_array is
    array (natural range 0 to (DATA_MEM_SZ - 1)) of word;
  signal storage : storage_array;
begin
  
  accessRAM: process(rst, clk, sel, wr, ender, data_inp)
    variable u_addr : t_address;
    variable index, latched : natural;

    variable d : reg32 := (others => '0');
    variable val, i : integer;

  begin

    if (rst = '0') and (sel = '1') then -- normal operation

      index := BV2INT16(ender);

      if  (wr = '1') and rising_edge(clk) then
        
        assert (index >= 0) and (index < DATA_MEM_SZ)
          report "ramWR index out of bounds: " & natural'image(index)
          severity failure;

        storage(index) <= data_inp;
        
        assert TRUE report "ramWR["& natural'image(index) &"] "
          & BV32HEX(data_inp); -- DEBUG
        
      else

        assert (index >= 0) and (index < DATA_MEM_SZ)
          report "ramRD index out of bounds: " & natural'image(index)
          severity failure;

        d := storage(index);
        
        assert TRUE report "ramRD["& natural'image(index) &"] "
          & BV32HEX(d);  -- DEBUG

      end if; -- normal operation

      data_out <= d;

    else

      data_out <= (others=>'0');

    end if; -- is reset?
    
  end process accessRAM; -- ---------------------------------------------
  
end rtl;
-- -----------------------------------------------------------------------



-- +++++++++++++++++++++++++++++++++++++++++++++++++++++++++++++++++++
-- banco de registradores
--          NAO ALTERE ESTE MODELO
-- +++++++++++++++++++++++++++++++++++++++++++++++++++++++++++++++++++
use work.p_wires.all;

entity R is
  port (clk         : in  bit;
        wr_en       : in  bit;          -- ativo em 1
        r_a,r_b,r_c : in  reg4;
        A,B         : out reg32;
        C           : in  reg32);
end R;

architecture rtl of R is
  type reg_file is array(0 to 15) of reg32;
  signal reg_file_A : reg_file;
  signal reg_file_B : reg_file;
  signal int_ra, int_rb, int_rc : integer range 0 to 15;
begin

  int_ra <= BV2INT4(r_a);
  int_rb <= BV2INT4(r_b);
  int_rc <= BV2INT4(r_c);

  A <= reg_file_A( int_ra ) when r_a /= b"0000" else
       x"00000000";                        -- reg0 always zero
  B <= reg_file_B( int_rb ) when r_b /= b"0000" else
       x"00000000";

  WRITE_REG_BANKS: process(clk)
  begin
    if rising_edge(clk) then
      if wr_en = '1' and r_c /= b"0000" then
        reg_file_A( int_rc ) <= C;
        reg_file_B( int_rc ) <= C;
      end if;
    end if;
  end process WRITE_REG_BANKS;
  
end rtl;
-- -----------------------------------------------------------------------

projetos-digitais/trabalho/mem.vhd
-- ++++++++++++++++++++++++++++++++++++++++++++++++++++++++++++++++++++++++
-- UFPR, BCC, ci210 2019-2 trabalho semestral, autor: Roberto Hexsel, 14nov
-- ++++++++++++++++++++++++++++++++++++++++++++++++++++++++++++++++++++++++

use work.p_wires.all;

entity mem_prog is
  port (ender : in  reg7;
        instr : out reg32);

  type t_prog_mem is array (0 to 127) of reg32;

  -- memoria de programa contem somente 128 palavras
  constant program : t_prog_mem := (

    x"800efffe", -- main:	addi sp, r0, fffe       0x00 # inicializa sp
    x"80040004", -- 		addi r4, r0, 4          0x01 # i (r4) <- 4 
    x"c400000c", -- for:	bran r4, r0, fim        0x02 # if i == 0 -> branch to fim
    x"b040ffff", -- 		show r4                 0x03 # print i
    x"84020000", -- 		addi a0, r4, 0          0x04 # move i pra argumento a0
    x"80030004", -- 		addi a1, r0, 4          0x05 # move 4 pra argumento a1
    x"d00f000d", -- 		jal power               0x06 # chama funcao power
    x"81020000", -- 		addi a0, v0, 0          0x08 # move resultado de power pra argumento a0
    x"d00f001d", -- 		jal log                 0x08 # chama funcao log2
    x"b010ffff", -- 		show v0                 0x09 # imprime resultado
    x"8404ffff", -- 		addi r4, r4, -1         0x0a # i = i - 1
    x"c0000002", -- 		bran: for               0x0b # volta pro loop
    x"f0000000", -- fim:	halt                    0x0c # fim do main


    x"8e0efffe", -- power:	addi sp, sp, -2         0x0d # aloca espaco na pilha
    x"be400001", -- 		st r4, 1(sp)            0x0e # salva registrador r4 para ser utilizado
    x"80040001", -- 		addi r4, r0, 1          0x0f # r4 <- 1
    x"c3400019", -- 		bran a1, r4, return     0x10 # se exp = 1, sai da funcao
    x"bef00000", -- 		st ra, 0(sp)            0x11 # salva o return address
    x"8303ffff", -- 		addi a1, a1, -1         0x12 # exp - 1
    x"d00f000d", -- 		jal power               0x13 # chamada recursiva
    x"31210000", -- 		mul v0, v0, a0          0x14 # n * resultado recursivo anterior
    x"ae0f0000", -- 		ld ra, 0(sp)            0x15 # load no return address
    x"ae040001", -- 		ld r4, 1(sp)            0x16 # load no r4
    x"8e0e0002", -- 		addi sp, sp, 2          0x17 # libera o espaco na pilha
    x"ef000000", -- 		jr ra                   0x18 # volta da funcao
    x"82010000", -- return:	addi v0, a0, 0          0x19 # retorna n
    x"ae040001", --	 	ld r4, 1(sp)            0x1a # load no r4
    x"8e0e0002", --		addi sp, sp, 2          0x1b # libera o espaco na pilha
    x"ef000000", --		jr ra                   0x1c # volta da funcao


    x"8e0efffe", -- log:	addi sp, sp, -2         0x1d # aloca espaco na pilha
    x"be400001", -- 		st r4, 1(sp)            0x1e # salva registrador r4 pra ser utilizado
    x"80040001", -- 		addi r4, r0, 1          0x1f # r4 <- 1
    x"c2400029", -- 		bran a0, r4, end        0x20 # se n = 1, retorna
    x"92420000", -- 		sra a0, a0, r4          0x21 # n = n / 2
    x"bef00000", -- 		st ra, 0(sp)            0x22 # salva o return address
    x"d00f001d", -- 		jal log                 0x23 # chamada recursiva
    x"81010001", -- 		addi v0, v0, 1          0x24 # retorna 1 + resultado anterior
    x"ae0f0000", -- 		ld ra, 0(sp)            0x25 # load no return address
    x"ae040001", -- 		ld r4, 1(sp)            0x26 # load no r4
    x"8e0e0002", -- 		addi sp, sp, 2          0x27 # libera o espaco na pilha
    x"ef000000", -- 		jr ra                   0x28 # volta da funcao
    x"80010000", -- end:	addi v0, r0, 0          0x29 # retorna 0
    x"ae040001", -- 		ld r4, 1(sp)            0x2a # load no r4
    x"8e0e0002", -- 		addi sp, sp, 2          0x2b # libera o espaco na pilha
    x"ef000000", -- 		jr ra                   0x2c # volta da funcao
    x"00000000",
    x"00000000",
    x"00000000",
    x"00000000",
    x"00000000",
    x"00000000",
    x"00000000",
    x"00000000",
    x"00000000",
    x"00000000",
    x"00000000",
    x"00000000",
    x"00000000",
    x"00000000",
    x"00000000",
    x"00000000",
    x"00000000",
    x"00000000",
    x"00000000",
    x"00000000",
    x"00000000",
    x"00000000",
    x"00000000",
    x"00000000",
    x"00000000",
    x"00000000",
    x"00000000",
    x"00000000",
    x"00000000",
    x"00000000",
    x"00000000",
    x"00000000",
    x"00000000",
    x"00000000",
    x"00000000",
    x"00000000",
    x"00000000",
    x"00000000",
    x"00000000",
    x"00000000",
    x"00000000",
    x"00000000",
    x"00000000",
    x"00000000",
    x"00000000",
    x"00000000",
    x"00000000",
    x"00000000",
    x"00000000",
    x"00000000",
    x"00000000",
    x"00000000",
    x"00000000",
    x"00000000",
    x"00000000",
    x"00000000",
    x"00000000",
    x"00000000",
    x"00000000",
    x"00000000",
    x"00000000",
    x"00000000",
    x"00000000",
    x"00000000",
    x"00000000",
    x"00000000",
    x"00000000",
    x"00000000",
    x"00000000",
    x"00000000",
    x"00000000",
    x"00000000",
    x"00000000",
    x"00000000",
    x"00000000",
    x"00000000",
    x"00000000",
    x"00000000",
    x"00000000",
    x"00000000",
    x"00000000",
    x"00000000",
    x"00000000"
  );


  function BV2INT7(S: reg7) return integer is
    variable result: integer;
  begin
    for i in S'range loop
      result := result * 2;
      if S(i) = '1' then
        result := result + 1;
      end if;
    end loop;
    return result;
  end BV2INT7;
  
end mem_prog;

-- nao altere esta arquitetura
architecture tabela of mem_prog is
begin  -- tabela

  instr <= program( BV2INT7(ender) );

end tabela;

projetos-digitais/trabalho/tb_mico.vhd
-- ++++++++++++++++++++++++++++++++++++++++++++++++++++++++++++++++++++++++
-- UFPR, BCC, ci210 2017-2 trabalho semestral, autor: Roberto Hexsel, 20out
-- ++++++++++++++++++++++++++++++++++++++++++++++++++++++++++++++++++++++++

--++++++++++++++++++++++++++++++++++++++++++++++++++++++++++++++++++++++++
-- testbench para Mico X
--++++++++++++++++++++++++++++++++++++++++++++++++++++++++++++++++++++++++
use work.p_wires.all;

entity tb_mico is
end tb_mico;

architecture TB of tb_mico is

  component mico is
    port (rst,clk : in    bit);
  end component mico;

  signal clk,rst : bit;
  
begin  -- TB

  U_mico: mico port map (rst,clk);

  U_clock: process
  begin
    clk <= '1';      -- executa e
    wait for t_clock_period / 2;  -- espera meio ciclo
    clk <= '0';      -- volta a executar e
    wait for t_clock_period / 2;  -- espera meio ciclo e volta ao topo
  end process;

  U_reset: process
  begin
    rst <= '1';      -- executa e
    wait for t_clock_period * 0.25;  -- espera por 1/4 de ciclo
    rst <= '0';      -- volta a executar e
    wait;            -- espera para sempre
  end process;
  
end TB;
-- ++++++++++++++++++++++++++++++++++++++++++++++++++++++++++++++++++++++


----------------------------------------------------------------
configuration CFG_TB of tb_mico is
	for TB
        end for;
end CFG_TB;
----------------------------------------------------------------

projetos-digitais/trabalho/v_mico.vcd
$date
  Tue Dec  3 17:42:15 2019
$end
$version
  GHDL v0
$end
$timescale
  1 fs
$end
$scope module standard $end
$upscope $end
$scope module std_logic_1164 $end
$upscope $end
$scope module numeric_std $end
$upscope $end
$scope module textio $end
$upscope $end
$scope module p_wires $end
$upscope $end
$scope module tb_mico $end
$var reg 1 ! clk $end
$var reg 1 " rst $end
$scope module u_mico $end
$var reg 1 # rst $end
$var reg 1 $ clk $end
$var reg 2 % selc[1:0] $end
$var reg 1 & selbeta $end
$var reg 1 ' wr_display $end
$var reg 1 ( wr_reg $end
$var reg 1 ) is_mem $end
$var reg 1 * mem_sel $end
$var reg 1 + mem_wr $end
$var reg 32 , instr[31:0] $end
$var reg 32 - a[31:0] $end
$var reg 32 . b[31:0] $end
$var reg 32 / c[31:0] $end
$var reg 32 0 beta[31:0] $end
$var reg 32 1 extended[31:0] $end
$var reg 32 2 ula_d[31:0] $end
$var reg 32 3 mem_d[31:0] $end
$comment this is not handled $end
$var reg 16 4 const[15:0] $end
$var reg 16 5 ip[15:0] $end
$var reg 16 6 ip_mais1[15:0] $end
$var reg 16 7 ext_zeros[15:0] $end
$var reg 16 8 ext_sinal[15:0] $end
$var reg 4 9 opcode[3:0] $end
$var integer 32 : i_opcode $end
$var reg 4 ; reg_a[3:0] $end
$var reg 4 < reg_b[3:0] $end
$var reg 4 = reg_c[3:0] $end
$scope module u_mem_prog $end
$var reg 7 > ender[6:0] $end
$var reg 32 ? instr[31:0] $end
$upscope $end
$scope module u_regs $end
$var reg 1 @ clk $end
$var reg 1 A wr_en $end
$var reg 4 B r_a[3:0] $end
$var reg 4 C r_b[3:0] $end
$var reg 4 D r_c[3:0] $end
$var reg 32 E a[31:0] $end
$var reg 32 F b[31:0] $end
$var reg 32 G c[31:0] $end
$comment reg_file_a is not handled $end
$comment reg_file_b is not handled $end
$var integer 32 H int_ra $end
$var integer 32 I int_rb $end
$var integer 32 J int_rc $end
$upscope $end
$scope module u_ula $end
$var reg 4 K fun[3:0] $end
$var reg 32 L alfa[31:0] $end
$var reg 32 M beta[31:0] $end
$var reg 32 N gama[31:0] $end
$var integer 32 O a $end
$var integer 32 P b $end
$var integer 32 Q c $end
$var integer 32 R sh_pos $end
$upscope $end
$scope module u_mem $end
$var reg 1 S rst $end
$var reg 1 T clk $end
$var reg 1 U sel $end
$var reg 1 V wr $end
$var reg 16 W ender[15:0] $end
$var reg 32 X data_inp[31:0] $end
$var reg 32 Y data_out[31:0] $end
$comment storage is not handled $end
$upscope $end
$scope module u_display $end
$var reg 1 Z rst $end
$var reg 1 [ clk $end
$var reg 1 \ enable $end
$var reg 32 ] data[31:0] $end
$upscope $end
$upscope $end
$upscope $end
$enddefinitions $end
#0
1!
1"
1#
1$
b00 %
1&
0'
1(
0)
0*
0+
b10000000000011101111111111111110 ,
b00000000000000000000000000000000 -
b00000000000000000000000000000000 .
b11111111111111111111111111111110 /
b11111111111111111111111111111110 0
b11111111111111111111111111111110 1
b11111111111111111111111111111110 2
b00000000000000000000000000000000 3
b1111111111111110 4
b0000000000000000 5
b0000000000000000 6
b0000000000000000 7
b1111111111111111 8
b1000 9
b1000 :
b0000 ;
b0000 <
b1110 =
b0000000 >
b10000000000011101111111111111110 ?
1@
1A
b0000 B
b0000 C
b1110 D
b00000000000000000000000000000000 E
b00000000000000000000000000000000 F
b11111111111111111111111111111110 G
b0 H
b0 I
b1110 J
b1000 K
b00000000000000000000000000000000 L
b11111111111111111111111111111110 M
b11111111111111111111111111111110 N
b0 O
b11111111111111111111111111111110 P
b10000000000000000000000000000000 Q
b11110 R
1S
1T
0U
0V
b1111111111111110 W
b00000000000000000000000000000000 X
b00000000000000000000000000000000 Y
1Z
1[
0\
b00000000000000000000000000000000 ]
#250000
0"
0#
0S
0Z
#500000
0!
0$
0@
0T
0[
#1000000
1!
1$
b10000000000001000000000000000100 ,
b00000000000000000000000000000100 /
b00000000000000000000000000000100 0
b00000000000000000000000000000100 1
b00000000000000000000000000000100 2
b0000000000000100 4
b0000000000000001 5
b0000000000000010 6
b0000000000000000 8
b0100 =
b0000001 >
b10000000000001000000000000000100 ?
1@
b0100 D
b00000000000000000000000000000100 G
b100 J
b00000000000000000000000000000100 M
b00000000000000000000000000000100 N
b100 P
b100 R
1T
b0000000000000100 W
1[
#1500000
0!
0$
0@
0T
0[
#2000000
1!
1$
b11 %
0(
b11000100000000000000000000001100 ,
b00000000000000000000000000000100 -
b00000000000000000000000000000000 /
b00000000000000000000000000001100 0
b00000000000000000000000000001100 1
b00000000000000000000000000000000 2
b0000000000001100 4
b0000000000000010 5
b0000000000000011 6
b1100 9
b1100 :
b0100 ;
b0000 =
b0000010 >
b11000100000000000000000000001100 ?
1@
0A
b0100 B
b0000 D
b00000000000000000000000000000100 E
b00000000000000000000000000000000 G
b100 H
b0 J
b1100 K
b00000000000000000000000000000100 L
b00000000000000000000000000001100 M
b00000000000000000000000000000000 N
b100 O
b1100 P
b1100 R
1T
b0000000000000000 W
1[
#2500000
0!
0$
0@
0T
0[
#3000000
1!
1$
1'
1)
1+
b10110000010000001111111111111111 ,
b00000000000000000000000000000000 -
b00000000000000000000000000000100 .
b11111111111111111111111111111111 0
b11111111111111111111111111111111 1
b11111111111111111111111111111111 2
b1111111111111111 4
b0000000000000011 5
b1111111111111111 8
b1011 9
b1011 :
b0000 ;
b0100 <
b0000011 >
b10110000010000001111111111111111 ?
1@
b0000 B
b0100 C
b00000000000000000000000000000000 E
b00000000000000000000000000000100 F
b0 H
b100 I
b1011 K
b00000000000000000000000000000000 L
b11111111111111111111111111111111 M
b11111111111111111111111111111111 N
b0 O
b11111111111111111111111111111111 P
b11111 R
1T
1V
b1111111111111111 W
b00000000000000000000000000000100 X
1[
1\
b00000000000000000000000000000100 ]
#3500000
0!
0$
0@
0T
0[
#4000000
1!
1$
b00 %
0'
1(
0)
0+
b10000100000000100000000000000000 ,
b00000000000000000000000000000100 -
b00000000000000000000000000000000 .
b00000000000000000000000000000100 /
b00000000000000000000000000000000 0
b00000000000000000000000000000000 1
b00000000000000000000000000000100 2
b0000000000000000 4
b0000000000000100 5
b0000000000000101 6
b0000000000000000 8
b1000 9
b1000 :
b0100 ;
b0000 <
b0010 =
b0000100 >
b10000100000000100000000000000000 ?
1@
1A
b0100 B
b0000 C
b0010 D
b00000000000000000000000000000100 E
b00000000000000000000000000000000 F
b00000000000000000000000000000100 G
b100 H
b0 I
b10 J
b1000 K
b00000000000000000000000000000100 L
b00000000000000000000000000000000 M
b00000000000000000000000000000100 N
b100 O
b0 P
b0 R
1T
0V
b0000000000000100 W
b00000000000000000000000000000000 X
1[
0\
b00000000000000000000000000000000 ]
#4500000
0!
0$
0@
0T
0[
#5000000
1!
1$
b10000000000000110000000000000100 ,
b00000000000000000000000000000000 -
b00000000000000000000000000000100 0
b00000000000000000000000000000100 1
b0000000000000100 4
b0000000000000101 5
b0000000000000110 6
b0000 ;
b0011 =
b0000101 >
b10000000000000110000000000000100 ?
1@
b0000 B
b0011 D
b00000000000000000000000000000000 E
b0 H
b11 J
b00000000000000000000000000000000 L
b00000000000000000000000000000100 M
b0 O
b100 P
b100 R
1T
1[
#5500000
0!
0$
0@
0T
0[
#6000000
1!
1$
b10 %
b11010000000011110000000000001101 ,
b00000000000000000000000000000111 /
b00000000000000000000000000001101 0
b00000000000000000000000000001101 1
b00000000000000000000000000000000 2
b0000000000001101 4
b0000000000000110 5
b0000000000000111 6
b1101 9
b1101 :
b1111 =
b0000110 >
b11010000000011110000000000001101 ?
1@
b1111 D
b00000000000000000000000000000111 G
b1111 J
b1101 K
b00000000000000000000000000001101 M
b00000000000000000000000000000000 N
b1101 P
b1101 R
1T
b0000000000000000 W
1[
#6500000
0!
0$
0@
0T
0[
#7000000
1!
1$
b00 %
b10001110000011101111111111111110 ,
b11111111111111111111111111111110 -
b11111111111111111111111111111100 /
b11111111111111111111111111111110 0
b11111111111111111111111111111110 1
b11111111111111111111111111111100 2
b1111111111111110 4
b0000000000001101 5
b1111111111111111 8
b1000 9
b1000 :
b1110 ;
b1110 =
b0001101 >
b10001110000011101111111111111110 ?
1@
b1110 B
b1110 D
b11111111111111111111111111111110 E
b11111111111111111111111111111100 G
b1110 H
b1110 J
b1000 K
b11111111111111111111111111111110 L
b11111111111111111111111111111110 M
b11111111111111111111111111111100 N
b11111111111111111111111111111110 O
b11111111111111111111111111111110 P
b11110 R
1T
b1111111111111100 W
1[
#7500000
0!
0$
0@
0T
0[
#8000000
1!
1$
b11 %
0(
1)
1*
1+
b10111110010000000000000000000001 ,
b11111111111111111111111111111100 -
b00000000000000000000000000000100 .
b00000000000000000000000000000000 /
b00000000000000000000000000000001 0
b00000000000000000000000000000001 1
b11111111111111111111111111111101 2
b0000000000000001 4
b0000000000001110 5
b0000000000001111 6
b0000000000000000 8
b1011 9
b1011 :
b0100 <
b0000 =
b0001110 >
b10111110010000000000000000000001 ?
1@
0A
b0100 C
b0000 D
b11111111111111111111111111111100 E
b00000000000000000000000000000100 F
b00000000000000000000000000000000 G
b100 I
b0 J
b1011 K
b11111111111111111111111111111100 L
b00000000000000000000000000000001 M
b11111111111111111111111111111101 N
b11111111111111111111111111111100 O
b1 P
b1 R
1T
1U
1V
b1111111111111101 W
b00000000000000000000000000000100 X
1[
b00000000000000000000000000000100 ]
#8500000
0!
0$
0@
0T
0[
#9000000
1!
1$
b00 %
1(
0)
0*
0+
b10000000000001000000000000000001 ,
b00000000000000000000000000000000 -
b00000000000000000000000000000000 .
b00000000000000000000000000000001 /
b00000000000000000000000000000001 2
b00000000000000000000000000000000 3
b0000000000001111 5
b0000000000010000 6
b1000 9
b1000 :
b0000 ;
b0000 <
b0100 =
b0001111 >
b10000000000001000000000000000001 ?
1@
1A
b0000 B
b0000 C
b0100 D
b00000000000000000000000000000000 E
b00000000000000000000000000000000 F
b00000000000000000000000000000001 G
b0 H
b0 I
b100 J
b1000 K
b00000000000000000000000000000000 L
b00000000000000000000000000000001 N
b0 O
1T
0U
0V
b0000000000000001 W
b00000000000000000000000000000000 X
b00000000000000000000000000000000 Y
1[
b00000000000000000000000000000000 ]
#9500000
0!
0$
0@
0T
0[
#10000000
1!
1$
b11 %
0(
b11000011010000000000000000011001 ,
b00000000000000000000000000000100 -
b00000000000000000000000000000001 .
b00000000000000000000000000000000 /
b00000000000000000000000000011001 0
b00000000000000000000000000011001 1
b00000000000000000000000000000000 2
b0000000000011001 4
b0000000000010000 5
b0000000000010001 6
b1100 9
b1100 :
b0011 ;
b0100 <
b0000 =
b0010000 >
b11000011010000000000000000011001 ?
1@
0A
b0011 B
b0100 C
b0000 D
b00000000000000000000000000000100 E
b00000000000000000000000000000001 F
b00000000000000000000000000000000 G
b11 H
b100 I
b0 J
b1100 K
b00000000000000000000000000000100 L
b00000000000000000000000000011001 M
b00000000000000000000000000000000 N
b100 O
b11001 P
b11001 R
1T
b0000000000000000 W
b00000000000000000000000000000001 X
1[
b00000000000000000000000000000001 ]
#10500000
0!
0$
0@
0T
0[
#11000000
1!
1$
1)
1*
1+
b10111110111100000000000000000000 ,
b11111111111111111111111111111100 -
b00000000000000000000000000000111 .
b00000000000000000000000000000000 0
b00000000000000000000000000000000 1
b11111111111111111111111111111100 2
b0000000000000000 4
b0000000000010001 5
b1011 9
b1011 :
b1110 ;
b1111 <
b0010001 >
b10111110111100000000000000000000 ?
1@
b1110 B
b1111 C
b11111111111111111111111111111100 E
b00000000000000000000000000000111 F
b1110 H
b1111 I
b1011 K
b11111111111111111111111111111100 L
b00000000000000000000000000000000 M
b11111111111111111111111111111100 N
b11111111111111111111111111111100 O
b0 P
b0 R
1T
1U
1V
b1111111111111100 W
b00000000000000000000000000000111 X
1[
b00000000000000000000000000000111 ]
#11500000
0!
0$
0@
0T
0[
