projetos-digitais/vhdl/maqEst/aux.vhd
-- ++++++++++++++++++++++++++++++++++++++++++++++++++++++++++++++++++++++++
-- UFPR, BCC, ci210 2018-2 lab Maq Estados, autor: Roberto Hexsel, 10set
-- ++++++++++++++++++++++++++++++++++++++++++++++++++++++++++++++++++++++++

-- ESTE ARQUIVO NAO PODE SER ALTERADO

-- +++++++++++++++++++++++++++++++++++++++++++++++++++++++++++++++++++
-- inversor
-- +++++++++++++++++++++++++++++++++++++++++++++++++++++++++++++++++++
use work.p_wires.all;

entity inv is
  generic (prop : time := t_inv);
  port(A : in bit;
       S : out bit);
end inv;

architecture comport of inv is 
begin
    S <= (not A) after prop;
end architecture comport;
-- +++++++++++++++++++++++++++++++++++++++++++++++++++++++++++++++++++

-- +++++++++++++++++++++++++++++++++++++++++++++++++++++++++++++++++++
-- porta AND de 2 entradas
-- +++++++++++++++++++++++++++++++++++++++++++++++++++++++++++++++++++
use work.p_wires.all;

entity and2 is
  generic (prop : time := t_and2);
  port(A, B : in  bit;  -- entradas A,B
       S    : out bit); -- saida C
end and2;

architecture and2 of and2 is 
begin
    S <= A and B after prop;
end and2;
-- +++++++++++++++++++++++++++++++++++++++++++++++++++++++++++++++++++

-- +++++++++++++++++++++++++++++++++++++++++++++++++++++++++++++++++++
-- porta OR de 2 entradas
-- +++++++++++++++++++++++++++++++++++++++++++++++++++++++++++++++++++
use work.p_wires.all;

entity or2 is
  generic (prop : time := t_or2);
  port(A,B : in bit;
       S   : out bit);
end or2;

architecture comport of or2 is 
begin
  S <= reject t_rej inertial (A or B) after prop;
end architecture comport;
-- +++++++++++++++++++++++++++++++++++++++++++++++++++++++++++++++++++

-- +++++++++++++++++++++++++++++++++++++++++++++++++++++++++++++++++++
-- porta OR de 3 entradas
-- +++++++++++++++++++++++++++++++++++++++++++++++++++++++++++++++++++
use work.p_wires.all;

entity or3 is
  generic (prop : time := t_or3);
  port(A, B, C : in  bit;  -- entradas A,B,C
       S       : out bit); -- saida S 
end or3;

architecture or3 of or3 is 
begin
    S <= A or B or C after prop;
end or3;
-- +++++++++++++++++++++++++++++++++++++++++++++++++++++++++++++++++++

-- +++++++++++++++++++++++++++++++++++++++++++++++++++++++++++++++++++
-- porta XOR de 2 entradas
-- +++++++++++++++++++++++++++++++++++++++++++++++++++++++++++++++++++
use work.p_wires.all;

entity xor2 is
  port(A,B : in bit;
       S   : out bit);
end xor2;

architecture comport of xor2 is 
begin
  S <= reject t_rej inertial (A xor B) after t_xor2;
end architecture comport;
-- +++++++++++++++++++++++++++++++++++++++++++++++++++++++++++++++++++


-- +++++++++++++++++++++++++++++++++++++++++++++++++++++++++++++++++++
-- porta XOR de 3 entradas
-- +++++++++++++++++++++++++++++++++++++++++++++++++++++++++++++++++++
use work.p_wires.all;

entity xor3 is
  generic (prop : time := t_xor3);
  port(A, B, C : in  bit;   -- entradas A,B,C
       S       : out bit);  -- saida S 
end xor3;

architecture xor3 of xor3 is 
begin
    S <= A xor B xor C after prop;
end xor3;
-- +++++++++++++++++++++++++++++++++++++++++++++++++++++++++++++++++++


-- +++++++++++++++++++++++++++++++++++++++++++++++++++++++++++++++++++
-- mux2(a,b,s,z)
-- +++++++++++++++++++++++++++++++++++++++++++++++++++++++++++++++++++
use work.p_wires.all;

entity mux2 is
  port(A,B : in  bit;
       S   : in  bit;
       Z   : out bit);
end mux2;

architecture estrut of mux2 is 
  component inv is
    generic (prop : time);
    port(A : in bit; S : out bit);
  end component inv;
  component and2 is
    generic (prop : time);
    port(A,B : in bit; S : out bit);
  end component and2;
  component or2 is
    generic (prop : time);
    port(A,B : in bit; S : out bit);
  end component or2;
  signal negs,f0,f1 : bit;
 begin

  Ui:  inv  generic map (t_inv)  port map(s,negs);
  Ua0: and2 generic map (t_and2) port map(a,negs,f0);
  Ua1: and2 generic map (t_and2) port map(b,s,f1);
  Uor: or2  generic map (t_or2)  port map(f0,f1,z);
    
end architecture estrut;
-- +++++++++++++++++++++++++++++++++++++++++++++++++++++++++++++++++++


-- +++++++++++++++++++++++++++++++++++++++++++++++++++++++++++++++++++
-- flip-flop tipo D com set,reset=0 assincronos
-- +++++++++++++++++++++++++++++++++++++++++++++++++++++++++++++++++++
use work.p_WIRES.all;
entity FFD is
  port(clk, rst, set : in bit;
        D : in  bit;
        Q : out bit);
end FFD;

architecture funcional of FFD is
  signal estado : bit := '0';
begin

  process(clk, rst, set)
  begin
    if rst = '0' then
      estado <= '0';
    elsif set = '0' then
      estado <= '1';
    elsif rising_edge(clk) then
      estado <= D;
    end if;
  end process;

  Q <= estado after t_FFD;

end funcional;
-- +++++++++++++++++++++++++++++++++++++++++++++++++++++++++++++++++++


-- +++++++++++++++++++++++++++++++++++++++++++++++++++++++++++++++++++
-- flip-flop tipo D com set,reset=0 assincronos, saidas Q e /Q
-- +++++++++++++++++++++++++++++++++++++++++++++++++++++++++++++++++++
use work.p_WIRES.all;
entity FFDQQ is
  port(clk, rst, set : in bit;
        D    : in  bit;
        Q, N : out bit);
end FFDQQ;

architecture funcional of FFDQQ is
  signal estado : bit := '0';
begin

  process(clk, rst, set)
  begin
    if rst = '0' then
      estado <= '0';
    elsif set = '0' then
      estado <= '1';
    elsif rising_edge(clk) then
      estado <= D;
    end if;
  end process;

  Q <= estado after t_FFD;
  N <= not estado after t_FFD;

end funcional;
-- +++++++++++++++++++++++++++++++++++++++++++++++++++++++++++++++++++


-- +++++++++++++++++++++++++++++++++++++++++++++++++++++++++++++++++++
-- registrador de 32 bits, reset=0 assincrono, load=1 sincrono
-- +++++++++++++++++++++++++++++++++++++++++++++++++++++++++++++++++++
use work.p_WIRES.all;

entity registrador32 is
  port(clk, rst, ld: in  bit;
        D:           in  reg32;
        Q:           out reg32);
end registrador32;

architecture funcional of registrador32 is
  signal value: reg32;
begin

  process(clk, rst, ld)
  begin
    if rst = '0' then
      value <= x"00000000";
    elsif ld = '1' and rising_edge(clk) then
      value <= D;
    end if;
  end process;

  Q <= value after t_FFD;
end funcional;
-- +++++++++++++++++++++++++++++++++++++++++++++++++++++++++++++++++++


-- +++++++++++++++++++++++++++++++++++++++++++++++++++++++++++++++++++
-- ULA
-- +++++++++++++++++++++++++++++++++++++++++++++++++++++++++++++++++++
library IEEE;
use IEEE.std_logic_1164.all;
use IEEE.numeric_std.all;
use work.p_wires.all;

entity ULA is
  port (alfa,beta : in  reg32;
        oper      : in  reg3;
        delta     : out reg32);
end entity ULA;

architecture functional of ULA is
  signal soma, prod: integer;
  signal b_soma, b_prod : reg32;
begin

  soma   <= BV2INT(alfa) + BV2INT(beta);
  b_soma <= SLV2BV32( std_logic_vector(to_signed(soma,32)) );

  prod   <= BV2INT(alfa) * BV2INT(beta);
  b_prod <= SLV2BV32( std_logic_vector(to_signed(prod,32)) );
  
  with oper select
    delta <= alfa xor beta when "000",
             alfa and beta when "001",
             alfa or  beta when "010",
             b_soma        when "011",
             b_prod        when "100",
             x"00000000" when others;

end functional;
-- +++++++++++++++++++++++++++++++++++++++++++++++++++++++++++++++++++


--++++++++++++++++++++++++++++++++++++++++++++++++++++++++++++++++++++++++
-- escreve um inteiro na saida padrao do simulador
--++++++++++++++++++++++++++++++++++++++++++++++++++++++++++++++++++++++++
library IEEE;
use IEEE.std_logic_1164.all;
use IEEE.numeric_std.all;
use std.textio.all;
use work.p_wires.all;

entity write_int is
  port (rst, clk : in    bit;
        sel   : in    bit;              -- active in '1'
        data  : in    reg32);
end write_int;

architecture behavioral of write_int is

  file output : text open write_mode is "STD_OUTPUT";
  
begin

  U_write_uint: process(clk, sel)
    variable msg : line;
  begin
    
    if rising_edge(clk) and sel = '1' then
      write ( msg, string'(BV32HEX(data)) );
      writeline( output, msg );
    end if;
      
  end process U_write_uint;

end behavioral;
-- +++++++++++++++++++++++++++++++++++++++++++++++++++++++++++++++++++++

projetos-digitais/vhdl/maqEst/reduz.vhd
-- ++++++++++++++++++++++++++++++++++++++++++++++++++++++++++++++++++++++++
-- UFPR, BCC, ci210 2018-2 labMaqEst, autor: Roberto Hexsel, 12set2018
-- ++++++++++++++++++++++++++++++++++++++++++++++++++++++++++++++++++++++++


-- +++++++++++++++++++++++++++++++++++++++++++++++++++++++++++++++++++
-- curcuito que computa reducoes
-- +++++++++++++++++++++++++++++++++++++++++++++++++++++++++++++++++++
use work.p_wires.all;

entity reduz is
  port (rst, clk : in    bit;
        valor    : in    bit_vector;
        saida    : out   bit_vector;
        sel      : out   bit);         -- active in '1'
end reduz;

architecture functional of reduz is

  component ULA
    port (alfa,beta : in  bit_vector;
          oper      : in  bit_vector;
          delta     : out bit_vector);
  end component ULA;

  component registrador32 is
    port(clk, rst, ld: in  bit;
         D:           in  reg32;
         Q:           out reg32);
  end component registrador32;

  -- por completar: acrescente tantos estados quantos necessarios
  type states is (st_sync, st_oper, st_digi0, st_digi1, st_digi2, st_digi3, st_digi4, st_digi5, st_digi6, st_digi7);

  signal curr_st, next_st : states;

  signal alfa, beta, delta, inp_red, oper32 : reg32;
  signal oper : reg3;
  signal ld_b, ld_op, init_b, sync, pronto : bit;
  signal dbg_st : integer;
  
begin  -- functional


  -- circuito de dados ---------------------------------------------

  sync     <= '1' when valor = x"ffffffff" else '0';

  U_oper: registrador32 port map(clk, rst, ld_op, valor, oper32);

  inp_red <= valor when init_b = '1' else delta;
  
  U_red:  registrador32 port map(clk, rst, ld_b, inp_red, beta);

  oper <= oper32(2 downto 0);
  alfa <= valor;
  
  U_ula:  ULA port map(alfa, beta, oper, delta);

  saida <= delta;


  -- maquina de estados ---------------------------------------------

  dbg_st <= integer(states'pos(curr_st));  -- debugging only

  U_state_reg: process(rst, clk)
  begin
    if rst = '0' then
      curr_st <= st_sync;
    elsif rising_edge(clk) then
      curr_st <= next_st;
    end if;
  end process U_state_reg;

  U_st_transitions: process(curr_st, sync)  -- por completar
  begin                  
    case curr_st is

      when st_sync =>          -- sync
        if sync = '1' then
          next_st <= st_sync;
        else
          next_st <= st_oper;
        end if;
        
      when st_oper =>          -- oper
        next_st <= st_digi0;

      when st_digi0 =>
       next_st <= st_digi1;

      when st_digi1 =>
       next_st <= st_digi2;

      when st_digi2 =>
       next_st <= st_digi3;

      when st_digi3 =>
       next_st <= st_digi4;

      when st_digi4 =>
       next_st <= st_digi5;

      when st_digi5 =>
       next_st <= st_digi6;

      when st_digi6 =>
       next_st <= st_digi7;

      when st_digi7 =>
	if sync = '1' then
          next_st <= st_sync;
	end if;

        -- complete a ME
        

    end case;
  end process U_st_transitions;

  
  U_output_fun: process(curr_st, sync)  -- por completar
  begin                  
    case curr_st is

      when st_sync =>
        if sync = '1' then
          ld_op  <= '0';  -- estes sinais sao Mealy
          ld_b   <= '0';
          init_b <= '0';
        else
          ld_op  <= '1';
          ld_b   <= '0';
          init_b <= '0';
        end if;
        sel    <= '0';      

      when st_oper =>     -- estes sinais são Moore
        ld_op  <= '0';
        ld_b   <= '1';
        init_b <= '1';        
        sel    <= '0';
        
      when st_digi0 =>
	ld_op  <= '0';
        ld_b   <= '1';
        init_b <= '0';
        sel    <= '0';

      when st_digi1 =>
        ld_op  <= '0';
        ld_b   <= '1';
        init_b <= '0';
        sel    <= '0';

      when st_digi2 =>
        ld_op  <= '0';
        ld_b   <= '1';
        init_b <= '0';
        sel    <= '0';

      when st_digi3 =>
        ld_op  <= '0';
        ld_b   <= '1';
        init_b <= '0';
        sel    <= '0';

      when st_digi4 =>
        ld_op  <= '0';
        ld_b   <= '1';
        init_b <= '0';
        sel    <= '0';

      when st_digi5 =>
        ld_op  <= '0';
        ld_b   <= '1';
        init_b <= '0';
        sel    <= '0';

      when st_digi6 =>
        ld_op  <= '0';
        ld_b   <= '0';
        init_b <= '0';
        sel    <= '1';

      when st_digi7 =>
        ld_op  <= '0';
        ld_b   <= '0';
        init_b <= '0';
        sel    <= '0';

        -- complete a funcao de saida
        
    end case;
  end process U_output_fun;


  
  
end functional;
-- +++++++++++++++++++++++++++++++++++++++++++++++++++++++++++++++++++

projetos-digitais/vhdl/maqEst/tb_reduz.vhd
-- ++++++++++++++++++++++++++++++++++++++++++++++++++++++++++++++++++++++++
-- UFPR, BCC, ci210 2018-2 lab Maq de Estado, autor: Roberto Hexsel, 10set
-- ++++++++++++++++++++++++++++++++++++++++++++++++++++++++++++++++++++++++

--++++++++++++++++++++++++++++++++++++++++++++++++++++++++++++++++++++++++
-- testbench do circuito que computa a redução de vetores
--++++++++++++++++++++++++++++++++++++++++++++++++++++++++++++++++++++++++
library ieee; use ieee.std_logic_1164.all;
use ieee.numeric_std.all;
use work.p_wires.all;

entity tb_reduz is
end tb_reduz;

architecture TB of tb_reduz is

  component write_int is
    port (rst,clk : in    bit;
          sel     : in    bit;         -- active in '1'
          data    : in    bit_vector);
  end component write_int;

  component reduz is
    port (rst,clk : in    bit;
          valor   : in    bit_vector;
          saida   : out   bit_vector;
          sel     : out   bit);         -- active in '1';
  end component reduz;

  type test_record is record
    entr : reg32;       -- entrada
    esp  : reg32;       -- TESTE: saida esperada
  end record test_record;

  type test_array is array(positive range <>) of test_record;
  
  constant test_vector : test_array := (
    -- nao altere estes tres primeiros --
    (x"ffffffff", x"00000000"), -- sync sync sync
    (x"ffffffff", x"00000000"),
    (x"ffffffff", x"00000000"),

    (x"00000004", x"00000000"), -- mult
    (x"00000001", x"00000000"),
    (x"00000002", x"00000000"),
    (x"00000003", x"00000000"),
    (x"00000004", x"00000000"), 
    (x"00000005", x"00000000"),
    (x"00000006", x"00000000"),
    (x"00000007", x"00000000"),
    (x"00000008", x"00009d80"), -- 0000.9d80 = 8!

    (x"ffffffff", x"00000000"), -- sync

    (x"00000003", x"00000000"), -- soma
    (x"11111111", x"00000000"),
    (x"22222222", x"00000000"),
    (x"33333333", x"00000000"),
    (x"00000000", x"00000000"),
    (x"11111111", x"00000000"),
    (x"00000000", x"00000000"),
    (x"11111111", x"00000000"),
    (x"11111111", x"99999999"), -- 9999.9999

    (x"ffffffff", x"00000000"), -- sync
    
    (x"00000002", x"00000000"), -- or
    (x"11110000", x"00000000"),
    (x"22220000", x"00000000"),
    (x"44440000", x"00000000"),
    (x"88880000", x"00000000"),
    (x"00001111", x"00000000"),
    (x"00002222", x"00000000"),
    (x"00004444", x"00000000"),
    (x"00008888", x"ffffffff"), -- ffff.ffff

    (x"ffffffff", x"00000000"), -- sync sync
    (x"ffffffff", x"00000000"),

    (x"00000001", x"00000000"), -- and
    (x"ffff7777", x"00000000"),
    (x"ffff3333", x"00000000"),
    (x"ffff1111", x"00000000"),
    (x"ffff5555", x"00000000"),
    (x"ffffffff", x"00000000"),
    (x"aaaa5555", x"00000000"),
    (x"5555ffff", x"00000000"),
    (x"1111ffff", x"00001111"), -- 0000.1111

    (x"ffffffff", x"00000000"), -- sync sync sync
    (x"ffffffff", x"00000000"),
    (x"ffffffff", x"00000000"), 

    (x"00000000", x"00000000"), -- xor
    (x"0000ffff", x"00000000"),
    (x"00005555", x"00000000"),
    (x"0000aaaa", x"00000000"),
    (x"00001111", x"00000000"),
    (x"11110000", x"00000000"),
    (x"22220000", x"00000000"),
    (x"44440000", x"00000000"),
    (x"88880000", x"ffff1111"), -- ffff.1111

    (x"ffffffff", x"00000000"), -- sync sync sync
    (x"ffffffff", x"00000000"), 
    (x"ffffffff", x"00000000"), 
    -- acrescente casos adicionais de teste aqui


    -- nao altere estes tres ultimos --
    (x"ffffffff", x"00000000"), -- sync sync sync
    (x"ffffffff", x"00000000"),
    (x"ffffffff", x"00000000")
    );
  
  signal clk, rst, w_sel: bit;
  signal entrada, saida, esp_res : reg32;
  signal fim_da_simulacao : boolean := false;
  
begin  -- TB

  U_reduz: reduz port map (rst, clk, entrada, saida, w_sel);

  U_write_output:  write_int port map (rst, clk, w_sel, saida);


  U_testValues: process                -- test the model
    variable v : test_record;
  begin

    fim_da_simulacao <= false;

    for i in test_vector'range loop
      
      v := test_vector(i);
      entrada <= v.entr;                -- valor na entrada
      esp_res <= v.esp;                 -- resultado esperado

      assert ( w_sel = '0' or saida = esp_res )
        report LF & LF & HT & "saida errada" &
               LF & HT      & "saida = " & BV32HEX(saida) &
               LF & HT      & "esper = " & BV32HEX(esp_res) & LF
        severity error;

      wait until rising_edge(clk);
      
    end loop;

    fim_da_simulacao <= true;
    wait;
    
  end process U_testValues;  

  
  U_clock: process
  begin
    clk <= '1';      -- executa e
    wait for t_clock_period / 2;  -- espera meio ciclo
    clk <= '0';      -- volta a executar e
    wait for t_clock_period / 2;  -- espera meio ciclo e volta ao topo

    if fim_da_simulacao then
      wait;          -- termina a simulacao
    end if;

  end process U_clock;


  U_reset: process
  begin
    rst <= '0';      -- executa e
    wait for t_clock_period * 0.75;  -- espera por 3/4 de ciclo
    rst <= '1';      -- volta a executar e
    wait;            -- espera para sempre
  end process u_reset;

end TB;
-- ++++++++++++++++++++++++++++++++++++++++++++++++++++++++++++++++++++++

----------------------------------------------------------------
configuration CFG_TB of tb_reduz is
	for TB
        end for;
end CFG_TB;
----------------------------------------------------------------

projetos-digitais/vhdl/maqEst/v_reduz.vcd
$date
  Thu Oct 24 11:21:46 2019
$end
$version
  GHDL v0
$end
$timescale
  1 fs
$end
$scope module standard $end
$upscope $end
$scope module std_logic_1164 $end
$upscope $end
$scope module numeric_std $end
$upscope $end
$scope module textio $end
$upscope $end
$scope module p_wires $end
$upscope $end
$scope module tb_reduz $end
$var reg 1 ! clk $end
$var reg 1 " rst $end
$var reg 1 # w_sel $end
$var reg 32 $ entrada[31:0] $end
$var reg 32 % saida[31:0] $end
$var reg 32 & esp_res[31:0] $end
$var reg 1 ' fim_da_simulacao $end
$scope module u_reduz $end
$var reg 1 ( rst $end
$var reg 1 ) clk $end
$var reg 32 * valor[31:0] $end
$var reg 32 + saida[31:0] $end
$var reg 1 , sel $end
$comment curr_st is not handled $end
$comment next_st is not handled $end
$var reg 32 - alfa[31:0] $end
$var reg 32 . beta[31:0] $end
$var reg 32 / delta[31:0] $end
$var reg 32 0 inp_red[31:0] $end
$var reg 32 1 oper32[31:0] $end
$var reg 3 2 oper[2:0] $end
$var reg 1 3 ld_b $end
$var reg 1 4 ld_op $end
$var reg 1 5 init_b $end
$var reg 1 6 sync $end
$var reg 1 7 pronto $end
$var integer 32 8 dbg_st $end
$scope module u_oper $end
$var reg 1 9 clk $end
$var reg 1 : rst $end
$var reg 1 ; ld $end
$var reg 32 < d[31:0] $end
$var reg 32 = q[31:0] $end
$var reg 32 > value[31:0] $end
$upscope $end
$scope module u_red $end
$var reg 1 ? clk $end
$var reg 1 @ rst $end
$var reg 1 A ld $end
$var reg 32 B d[31:0] $end
$var reg 32 C q[31:0] $end
$var reg 32 D value[31:0] $end
$upscope $end
$scope module u_ula $end
$var reg 32 E alfa[31:0] $end
$var reg 32 F beta[31:0] $end
$var reg 3 G oper[2:0] $end
$var reg 32 H delta[31:0] $end
$var integer 32 I soma $end
$var integer 32 J prod $end
$var reg 32 K b_soma[31:0] $end
$var reg 32 L b_prod[31:0] $end
$upscope $end
$upscope $end
$scope module u_write_output $end
$var reg 1 M rst $end
$var reg 1 N clk $end
$var reg 1 O sel $end
$var reg 32 P data[31:0] $end
$upscope $end
$upscope $end
$enddefinitions $end
#0
1!
0"
0#
b11111111111111111111111111111111 $
b11111111111111111111111111111111 %
b00000000000000000000000000000000 &
0'
0(
1)
b11111111111111111111111111111111 *
b11111111111111111111111111111111 +
0,
b11111111111111111111111111111111 -
b00000000000000000000000000000000 .
b11111111111111111111111111111111 /
b11111111111111111111111111111111 0
b00000000000000000000000000000000 1
b000 2
03
04
05
16
07
b0 8
19
0:
0;
b11111111111111111111111111111111 <
b00000000000000000000000000000000 =
b00000000000000000000000000000000 >
1?
0@
0A
b11111111111111111111111111111111 B
b00000000000000000000000000000000 C
b00000000000000000000000000000000 D
b11111111111111111111111111111111 E
b00000000000000000000000000000000 F
b000 G
b11111111111111111111111111111111 H
b11111111111111111111111111111111 I
b0 J
b11111111111111111111111111111111 K
b00000000000000000000000000000000 L
0M
1N
0O
b11111111111111111111111111111111 P
#500000
0!
0)
09
0?
0N
#750000
1"
1(
1:
1@
1M
#1000000
1!
1)
19
1?
1N
#1500000
0!
0)
09
0?
0N
#2000000
1!
b00000000000000000000000000000100 $
b00000000000000000000000000000100 %
1)
b00000000000000000000000000000100 *
b00000000000000000000000000000100 +
b00000000000000000000000000000100 -
b00000000000000000000000000000100 /
b00000000000000000000000000000100 0
14
06
19
1;
b00000000000000000000000000000100 <
1?
b00000000000000000000000000000100 B
b00000000000000000000000000000100 E
b00000000000000000000000000000100 H
b100 I
b00000000000000000000000000000100 K
1N
b00000000000000000000000000000100 P
#2500000
0!
0)
09
0?
0N
#3000000
1!
b00000000000000000000000000000001 $
b00000000000000000000000000000000 %
1)
b00000000000000000000000000000001 *
b00000000000000000000000000000000 +
b00000000000000000000000000000001 -
b00000000000000000000000000000000 /
b00000000000000000000000000000001 0
b00000000000000000000000000000100 1
b100 2
13
04
15
b1 8
19
0;
b00000000000000000000000000000001 <
b00000000000000000000000000000100 =
b00000000000000000000000000000100 >
1?
1A
b00000000000000000000000000000001 B
b00000000000000000000000000000001 E
b100 G
b00000000000000000000000000000000 H
b1 I
b00000000000000000000000000000001 K
1N
b00000000000000000000000000000000 P
#3500000
0!
0)
09
0?
0N
#4000000
1!
b00000000000000000000000000000010 $
b00000000000000000000000000000010 %
1)
b00000000000000000000000000000010 *
b00000000000000000000000000000010 +
b00000000000000000000000000000010 -
b00000000000000000000000000000001 .
b00000000000000000000000000000010 /
b00000000000000000000000000000010 0
05
b10 8
19
b00000000000000000000000000000010 <
1?
b00000000000000000000000000000010 B
b00000000000000000000000000000001 C
b00000000000000000000000000000001 D
b00000000000000000000000000000010 E
b00000000000000000000000000000001 F
b00000000000000000000000000000010 H
b11 I
b10 J
b00000000000000000000000000000011 K
b00000000000000000000000000000010 L
1N
b00000000000000000000000000000010 P
#4500000
0!
0)
09
0?
0N
#5000000
1!
b00000000000000000000000000000011 $
b00000000000000000000000000000110 %
1)
b00000000000000000000000000000011 *
b00000000000000000000000000000110 +
b00000000000000000000000000000011 -
b00000000000000000000000000000010 .
b00000000000000000000000000000110 /
b00000000000000000000000000000110 0
b11 8
19
b00000000000000000000000000000011 <
1?
b00000000000000000000000000000110 B
b00000000000000000000000000000010 C
b00000000000000000000000000000010 D
b00000000000000000000000000000011 E
b00000000000000000000000000000010 F
b00000000000000000000000000000110 H
b101 I
b110 J
b00000000000000000000000000000101 K
b00000000000000000000000000000110 L
1N
b00000000000000000000000000000110 P
#5500000
0!
0)
09
0?
0N
#6000000
1!
b00000000000000000000000000000100 $
b00000000000000000000000000011000 %
1)
b00000000000000000000000000000100 *
b00000000000000000000000000011000 +
b00000000000000000000000000000100 -
b00000000000000000000000000000110 .
b00000000000000000000000000011000 /
b00000000000000000000000000011000 0
b100 8
19
b00000000000000000000000000000100 <
1?
b00000000000000000000000000011000 B
b00000000000000000000000000000110 C
b00000000000000000000000000000110 D
b00000000000000000000000000000100 E
b00000000000000000000000000000110 F
b00000000000000000000000000011000 H
b1010 I
b11000 J
b00000000000000000000000000001010 K
b00000000000000000000000000011000 L
1N
b00000000000000000000000000011000 P
#6500000
0!
0)
09
0?
0N
#7000000
1!
b00000000000000000000000000000101 $
b00000000000000000000000001111000 %
1)
b00000000000000000000000000000101 *
b00000000000000000000000001111000 +
b00000000000000000000000000000101 -
b00000000000000000000000000011000 .
b00000000000000000000000001111000 /
b00000000000000000000000001111000 0
b101 8
19
b00000000000000000000000000000101 <
1?
b00000000000000000000000001111000 B
b00000000000000000000000000011000 C
b00000000000000000000000000011000 D
b00000000000000000000000000000101 E
b00000000000000000000000000011000 F
b00000000000000000000000001111000 H
b11101 I
b1111000 J
b00000000000000000000000000011101 K
b00000000000000000000000001111000 L
1N
b00000000000000000000000001111000 P
#7500000
0!
0)
09
0?
0N
#8000000
1!
b00000000000000000000000000000110 $
b00000000000000000000001011010000 %
1)
b00000000000000000000000000000110 *
b00000000000000000000001011010000 +
b00000000000000000000000000000110 -
b00000000000000000000000001111000 .
b00000000000000000000001011010000 /
b00000000000000000000001011010000 0
b110 8
19
b00000000000000000000000000000110 <
1?
b00000000000000000000001011010000 B
b00000000000000000000000001111000 C
b00000000000000000000000001111000 D
b00000000000000000000000000000110 E
b00000000000000000000000001111000 F
b00000000000000000000001011010000 H
b1111110 I
b1011010000 J
b00000000000000000000000001111110 K
b00000000000000000000001011010000 L
1N
b00000000000000000000001011010000 P
#8500000
0!
0)
09
0?
0N
#9000000
1!
b00000000000000000000000000000111 $
b00000000000000000001001110110000 %
1)
b00000000000000000000000000000111 *
b00000000000000000001001110110000 +
b00000000000000000000000000000111 -
b00000000000000000000001011010000 .
b00000000000000000001001110110000 /
b00000000000000000001001110110000 0
b111 8
19
b00000000000000000000000000000111 <
1?
b00000000000000000001001110110000 B
b00000000000000000000001011010000 C
b00000000000000000000001011010000 D
b00000000000000000000000000000111 E
b00000000000000000000001011010000 F
b00000000000000000001001110110000 H
b1011010111 I
b1001110110000 J
b00000000000000000000001011010111 K
b00000000000000000001001110110000 L
1N
b00000000000000000001001110110000 P
#9500000
0!
0)
09
0?
0N
#10000000
1!
1#
b00000000000000000000000000001000 $
b00000000000000001001110110000000 %
b00000000000000001001110110000000 &
1)
b00000000000000000000000000001000 *
b00000000000000001001110110000000 +
1,
b00000000000000000000000000001000 -
b00000000000000000001001110110000 .
b00000000000000001001110110000000 /
b00000000000000001001110110000000 0
03
b1000 8
19
b00000000000000000000000000001000 <
1?
0A
b00000000000000001001110110000000 B
b00000000000000000001001110110000 C
b00000000000000000001001110110000 D
b00000000000000000000000000001000 E
b00000000000000000001001110110000 F
b00000000000000001001110110000000 H
b1001110111000 I
b1001110110000000 J
b00000000000000000001001110111000 K
b00000000000000001001110110000000 L
1N
1O
b00000000000000001001110110000000 P
#10500000
0!
0)
09
0?
0N
#11000000
1!
0#
b11111111111111111111111111111111 $
b11111111111111111110110001010000 %
b00000000000000000000000000000000 &
1)
b11111111111111111111111111111111 *
b11111111111111111110110001010000 +
0,
b11111111111111111111111111111111 -
b11111111111111111110110001010000 /
b11111111111111111110110001010000 0
16
b1001 8
19
b11111111111111111111111111111111 <
1?
b11111111111111111110110001010000 B
b11111111111111111111111111111111 E
b11111111111111111110110001010000 H
b1001110101111 I
b11111111111111111110110001010000 J
b00000000000000000001001110101111 K
b11111111111111111110110001010000 L
1N
0O
b11111111111111111110110001010000 P
#11500000
0!
0)
09
0?
0N
#12000000
1!
b00000000000000000000000000000011 $
b00000000000000000011101100010000 %
1)
b00000000000000000000000000000011 *
b00000000000000000011101100010000 +
b00000000000000000000000000000011 -
b00000000000000000011101100010000 /
b00000000000000000011101100010000 0
14
06
b0 8
19
1;
b00000000000000000000000000000011 <
1?
b00000000000000000011101100010000 B
b00000000000000000000000000000011 E
b00000000000000000011101100010000 H
b1001110110011 I
b11101100010000 J
b00000000000000000001001110110011 K
b00000000000000000011101100010000 L
1N
b00000000000000000011101100010000 P
#12500000
0!
0)
09
0?
0N
#13000000
1!
b00010001000100010001000100010001 $
b00010001000100010010010011000001 %
1)
b00010001000100010001000100010001 *
b00010001000100010010010011000001 +
b00010001000100010001000100010001 -
b00010001000100010010010011000001 /
b00010001000100010001000100010001 0
b00000000000000000000000000000011 1
b011 2
13
04
15
b1 8
19
0;
b00010001000100010001000100010001 <
b00000000000000000000000000000011 =
b00000000000000000000000000000011 >
1?
1A
b00010001000100010001000100010001 B
b00010001000100010001000100010001 E
b011 G
b00010001000100010010010011000001 H
b10001000100010010010011000001 I
b11111111111111111111111010110000 J
b00010001000100010010010011000001 K
b11111111111111111111111010110000 L
1N
b00010001000100010010010011000001 P
#13500000
0!
0)
09
0?
0N
#14000000
1!
b00100010001000100010001000100010 $
b00110011001100110011001100110011 %
1)
b00100010001000100010001000100010 *
b00110011001100110011001100110011 +
b00100010001000100010001000100010 -
b00010001000100010001000100010001 .
b00110011001100110011001100110011 /
b00110011001100110011001100110011 0
05
b10 8
19
b00100010001000100010001000100010 <
1?
b00110011001100110011001100110011 B
b00010001000100010001000100010001 C
b00010001000100010001000100010001 D
b00100010001000100010001000100010 E
b00010001000100010001000100010001 F
b00110011001100110011001100110011 H
b110011001100110011001100110011 I
b1110110010101000011001000010 J
b00110011001100110011001100110011 K
b00001110110010101000011001000010 L
1N
b00110011001100110011001100110011 P
#14500000
0!
0)
09
0?
0N
#15000000
1!
b00110011001100110011001100110011 $
b01100110011001100110011001100110 %
1)
b00110011001100110011001100110011 *
b01100110011001100110011001100110 +
b00110011001100110011001100110011 -
b00110011001100110011001100110011 .
b01100110011001100110011001100110 /
b01100110011001100110011001100110 0
b11 8
19
b00110011001100110011001100110011 <
1?
b01100110011001100110011001100110 B
b00110011001100110011001100110011 C
b00110011001100110011001100110011 D
b00110011001100110011001100110011 E
b00110011001100110011001100110011 F
b01100110011001100110011001100110 H
b1100110011001100110011001100110 I
b11000010100011110101110000101001 J
b01100110011001100110011001100110 K
b11000010100011110101110000101001 L
1N
b01100110011001100110011001100110 P
#15500000
0!
0)
09
0?
0N
#16000000
1!
b00000000000000000000000000000000 $
1)
b00000000000000000000000000000000 *
b00000000000000000000000000000000 -
b01100110011001100110011001100110 .
b100 8
19
b00000000000000000000000000000000 <
1?
b01100110011001100110011001100110 C
b01100110011001100110011001100110 D
b00000000000000000000000000000000 E
b01100110011001100110011001100110 F
b0 J
b00000000000000000000000000000000 L
1N
#16500000
0!
0)
09
0?
0N
